kinetic_core/__init__.py
kinetic_core/auth/__init__.py
kinetic_core/auth/jwt_auth.py
kinetic_core/auth/oauth_auth.py
kinetic_core/core/__init__.py
kinetic_core/core/client.py
kinetic_core/core/session.py
kinetic_core/logging/__init__.py
kinetic_core/logging/logger.py
kinetic_core/mapping/__init__.py
kinetic_core/mapping/field_mapper.py
kinetic_core/pipeline/__init__.py
kinetic_core/pipeline/sync_pipeline.py
kinetic_core/utils/__init__.py
kinetic_core/utils/helpers.py
kinetic_core-1.1.0.dist-info/licenses/LICENSE
salesforce_toolkit/__init__.py
kinetic_core-1.1.0.dist-info/METADATA
kinetic_core-1.1.0.dist-info/WHEEL
kinetic_core-1.1.0.dist-info/entry_points.txt
kinetic_core-1.1.0.dist-info/top_level.txt
kinetic_core-1.1.0.dist-info/RECORD
