Metadata-Version: 2.4
Name: kinetic-core
Version: 1.1.0
Summary: The core engine for Salesforce AI agents
Home-page: https://github.com/antonio-backend-projects/kinetic-core
Author: Antonio Trento
Author-email: info@antoniotrento.net
Project-URL: Documentation, https://github.com/antonio-backend-projects/kinetic-core#readme
Project-URL: Source, https://github.com/antonio-backend-projects/kinetic-core
Project-URL: Bug Reports, https://github.com/antonio-backend-projects/kinetic-core/issues
Project-URL: Portfolio, https://antoniotrento.net/portfolio/kinetic-core/
Keywords: salesforce,crm,integration,api,etl,data-sync,rest-api,jwt,oauth,ai,agent,mcp
Classifier: Development Status :: 4 - Beta
Classifier: Intended Audience :: Developers
Classifier: Topic :: Software Development :: Libraries :: Python Modules
Classifier: Topic :: Office/Business
Classifier: License :: OSI Approved :: MIT License
Classifier: Programming Language :: Python :: 3
Classifier: Programming Language :: Python :: 3.8
Classifier: Programming Language :: Python :: 3.9
Classifier: Programming Language :: Python :: 3.10
Classifier: Programming Language :: Python :: 3.11
Classifier: Programming Language :: Python :: 3.12
Classifier: Operating System :: OS Independent
Requires-Python: >=3.8
License-File: LICENSE
Requires-Dist: requests>=2.31.0
Requires-Dist: PyJWT>=2.8.0
Requires-Dist: cryptography>=41.0.7
Requires-Dist: PyYAML>=6.0.1
Requires-Dist: python-dotenv>=1.0.0
Provides-Extra: dev
Requires-Dist: pytest>=7.4.3; extra == "dev"
Requires-Dist: pytest-cov>=4.1.0; extra == "dev"
Requires-Dist: black>=23.12.1; extra == "dev"
Requires-Dist: flake8>=7.0.0; extra == "dev"
Requires-Dist: mypy>=1.8.0; extra == "dev"
Requires-Dist: sphinx>=7.2.6; extra == "dev"
Requires-Dist: twine>=4.0.2; extra == "dev"
Requires-Dist: build>=1.0.3; extra == "dev"
Provides-Extra: database
Requires-Dist: mysql-connector-python>=8.0.33; extra == "database"
Requires-Dist: psycopg2-binary>=2.9.9; extra == "database"
Requires-Dist: pymongo>=4.6.1; extra == "database"
Provides-Extra: data
Requires-Dist: pandas>=2.1.4; extra == "data"
Requires-Dist: numpy>=1.26.3; extra == "data"
Dynamic: author
Dynamic: author-email
Dynamic: classifier
Dynamic: description
Dynamic: description-content-type
Dynamic: home-page
Dynamic: keywords
Dynamic: license-file
Dynamic: project-url
Dynamic: provides-extra
Dynamic: requires-dist
Dynamic: requires-python
Dynamic: summary
